MANIFEST.in
README.rst
setup.py
django_naturalsortfield.egg-info/PKG-INFO
django_naturalsortfield.egg-info/SOURCES.txt
django_naturalsortfield.egg-info/dependency_links.txt
django_naturalsortfield.egg-info/top_level.txt
django_naturalsortfield.egg-info/zip-safe
naturalsortfield/__init__.py
naturalsortfield/base/__init__.py
naturalsortfield/en/__init__.py
testproject/__init__.py
testproject/manage.py
testproject/project/__init__.py
testproject/project/settings.py
testproject/project/app/__init__.py
testproject/project/app/en/__init__.py
testproject/project/app/en/models.py
testproject/project/app/en/tests.py