Metadata-Version: 1.0
Name: django-naturalsortfield
Version: 0.7
Summary: Natural sorting for Django CharFields.
Home-page: https://github.com/nathforge/django-naturalsortfield
Author: Nathan Reynolds
Author-email: email@nreynolds.co.uk
License: UNKNOWN
Platform: UNKNOWN
